django_welkin/__init__.py
django_welkin/admin.py
django_welkin/apps.py
django_welkin/forms.py
django_welkin/management/__init__.py
django_welkin/management/commands/__init__.py
django_welkin/management/commands/welkin_load_configuration.py
django_welkin/management/commands/welkin_sync_models.py
django_welkin/migrations/0001_initial.py
django_welkin/migrations/0002_alter_configuration_id_alter_webhookmessage_id.py
django_welkin/migrations/0003_user_email_alter_configuration_id_and_more.py
django_welkin/migrations/0004_alter_configuration_id_alter_webhookmessage_id.py
django_welkin/migrations/__init__.py
django_welkin/models/__init__.py
django_welkin/models/base.py
django_welkin/models/calendar.py
django_welkin/models/cdt.py
django_welkin/models/chat.py
django_welkin/models/configuration.py
django_welkin/models/patient.py
django_welkin/models/user.py
django_welkin/models/webhook.py
django_welkin/urls.py
django_welkin/views.py
django_welkin-0.0.6.dist-info/LICENSE
django_welkin-0.0.6.dist-info/METADATA
django_welkin-0.0.6.dist-info/WHEEL
django_welkin-0.0.6.dist-info/RECORD
