Metadata-Version: 2.1
Name: django-welkin
Version: 0.0.6
Summary: A Django app interfacing with the Welkin API.
Home-page: https://pypi.org/project/django-welkin/
License: GPL-3.0-or-later
Author: Sam Morgan
Author-email: sam@lightmatter.com
Requires-Python: >=3.8,<4.0
Classifier: Environment :: Web Environment
Classifier: Framework :: Django
Classifier: Framework :: Django :: 4.0
Classifier: Intended Audience :: Developers
Classifier: License :: OSI Approved :: BSD License
Classifier: License :: OSI Approved :: GNU General Public License v3 or later (GPLv3+)
Classifier: Operating System :: OS Independent
Classifier: Programming Language :: Python
Classifier: Programming Language :: Python :: 3
Classifier: Programming Language :: Python :: 3.8
Classifier: Programming Language :: Python :: 3.9
Classifier: Programming Language :: Python :: 3.10
Classifier: Programming Language :: Python :: 3.11
Classifier: Topic :: Internet :: WWW/HTTP
Classifier: Topic :: Internet :: WWW/HTTP :: Dynamic Content
Requires-Dist: django-solo (>=2.0.0,<3.0.0)
Requires-Dist: welkin (>=0.0.8,<0.0.9)
Project-URL: Documentation, https://django-welkin.readthedocs.io/
Project-URL: Repository, https://github.com/lightmatter/django-welkin
